[{"__type__":"cc.SpriteFrame","content":{"name":"bg_time3","texture":"32iS4l/HJKob43j+GoiWqz","rect":[228,1,205,265],"offset":[-7,-6],"originalSize":[247,327],"capInsets":[0,0,0,0]}},{"__type__":"cc.SpriteFrame","content":{"name":"bg_time2","texture":"32iS4l/HJKob43j+GoiWqz","rect":[270,268,213,259],"offset":[-4,-2],"originalSize":[247,327],"rotated":1,"capInsets":[0,0,0,0]}},{"__type__":"cc.SpriteFrame","content":{"name":"bg_time4","texture":"32iS4l/HJKob43j+GoiWqz","rect":[1,272,215,267],"offset":[-8,-2],"originalSize":[247,327],"rotated":1,"capInsets":[0,0,0,0]}},{"__type__":"cc.SpriteFrame","content":{"name":"bg_time1","texture":"32iS4l/HJKob43j+GoiWqz","rect":[435,1,153,263],"offset":[-18,0],"originalSize":[247,327],"capInsets":[0,0,0,0]}},{"__type__":"cc.SpriteFrame","content":{"name":"time_count","texture":"32iS4l/HJKob43j+GoiWqz","rect":[2,2,585,484],"offset":[0,0],"originalSize":[589,488],"capInsets":[0,0,0,0]}},{"__type__":"cc.SpriteFrame","content":{"name":"bg_time5","texture":"32iS4l/HJKob43j+GoiWqz","rect":[1,1,225,269],"offset":[-2,-6],"originalSize":[247,327],"capInsets":[0,0,0,0]}}]